bikmis/__init__.py
bikmis/common.py
KMIS-0.2.7.dist-info/LICENCE.txt
KMIS-0.2.7.dist-info/METADATA
KMIS-0.2.7.dist-info/WHEEL
KMIS-0.2.7.dist-info/top_level.txt
KMIS-0.2.7.dist-info/RECORD
