Metadata-Version: 2.1
Name: KMIS
Version: 0.2.7
Summary: My own tester
Home-page: 
Author: Marast
Author-email: havlicek.mara@gmail.com
License: MIT
Classifier: License :: OSI Approved :: MIT License
Classifier: Programming Language :: Python :: 3.10
Classifier: Operating System :: OS Independent
Requires-Python: >=3.10
License-File: LICENCE.txt
Requires-Dist: bson >=0.5.10
Provides-Extra: dev
Requires-Dist: pytest >=7.0 ; extra == 'dev'
Requires-Dist: twine >=4.0.2 ; extra == 'dev'
